kipris_trademark_mcp-0.1.0.dist-info/licenses/LICENSE
mcp_server/__init__.py
mcp_server/auth.py
mcp_server/server.py
mcp_server/tools/__init__.py
mcp_server/tools/find_codes_by_product_name.py
mcp_server/tools/search_by_application_number.py
mcp_server/tools/search_by_registration_number.py
mcp_server/tools/search_by_trademark_name.py
kipris_trademark_mcp-0.1.0.dist-info/METADATA
kipris_trademark_mcp-0.1.0.dist-info/WHEEL
kipris_trademark_mcp-0.1.0.dist-info/entry_points.txt
kipris_trademark_mcp-0.1.0.dist-info/top_level.txt
kipris_trademark_mcp-0.1.0.dist-info/RECORD
