Metadata-Version: 2.4
Name: kipris-trademark-mcp
Version: 0.1.0
Summary: KIPRIS 상표 관련 기능을 제공하는 MCP 서버
Author-email: Song <song@songohip.com>
License: MIT
Project-URL: Homepage, https://github.com/patentsong/songohip.git
Project-URL: Repository, https://github.com/patentsong/songohip.git
Keywords: kipris,trademark,mcp,ai agent,intellectual property
Requires-Python: ~=3.12
License-File: LICENSE
Requires-Dist: fastmcp>=2.1.2
Requires-Dist: pydantic>=2.5.3
Requires-Dist: httpx>=0.28.1
Requires-Dist: lxml>=5.4.0
Requires-Dist: kipris-api-wrapper==0.1.0
Provides-Extra: dev
Requires-Dist: pytest>=8.0; extra == "dev"
Requires-Dist: pytest-asyncio>=0.23.0; extra == "dev"
Requires-Dist: pytest-cov>=5.0.0; extra == "dev"
Requires-Dist: pytest-mock>=3.14.0; extra == "dev"
Requires-Dist: python-dotenv>=1.0.0; extra == "dev"
Requires-Dist: build; extra == "dev"
Dynamic: license-file
